{
  "page_id": "33d35e21-8cf8-8143-85bd-d525894a88d7",
  "title": "AI Book Cover Creator - Design App Development for Weavy Platform",
  "database": "Manus_Memory_Sessions",
  "db_id": "5e51ded4-0b46-4a68-acc2-4e90886a2499",
  "created": "2026-04-09",
  "edited": "2026-04-09",
  "acquired_at": "2026-07-01T19:03:19Z",
  "properties": {
    "Length": "xl",
    "Language": "en",
    "Subthemes": "Weavy platform, Book cover generation, Hybrid automation, Authentication systems, UI automation, Workflow design",
    "Project": "yOS",
    "UID": "jrhRzGgvrCzLtezdHXURnC",
    "Date": "2026-01-19",
    "Themes": "AI automation, Design app development, Creative workflow, Platform integration",
    "Archived": "True",
    "Depth": "substantial",
    "Title": "AI Book Cover Creator - Design App Development for Weavy Platform"
  },
  "blocks_count": 50,
  "blocks": [
    {
      "object": "block",
      "id": "b0611c0c-ab22-466e-a93c-7f4d654ff654",
      "parent": {
        "type": "page_id",
        "page_id": "33d35e21-8cf8-8143-85bd-d525894a88d7"
      },
      "created_time": "2026-04-09T08:40:00.000Z",
      "last_edited_time": "2026-04-09T08:40:00.000Z",
      "created_by": {
        "object": "user",
        "id": "8c4fdbe9-a093-423b-9b80-211cd139586b"
      },
      "last_edited_by": {
        "object": "user",
        "id": "8c4fdbe9-a093-423b-9b80-211cd139586b"
      },
      "has_children": false,
      "in_trash": false,
      "type": "heading_2",
      "heading_2": {
        "rich_text": [
          {
            "type": "text",
            "text": {
              "content": "Executive Summary",
              "link": null
            },
            "annotations": {
              "bold": false,
              "italic": false,
              "strikethrough": false,
              "underline": false,
              "code": false,
              "color": "default"
            },
            "plain_text": "Executive Summary",
            "href": null
          }
        ],
        "is_toggleable": false,
        "color": "default"
      },
      "archived": false
    },
    {
      "object": "block",
      "id": "fb29273c-f43e-4a5e-9ee9-0b65e8889c93",
      "parent": {
        "type": "page_id",
        "page_id": "33d35e21-8cf8-8143-85bd-d525894a88d7"
      },
      "created_time": "2026-04-09T08:40:00.000Z",
      "last_edited_time": "2026-04-09T08:40:00.000Z",
      "created_by": {
        "object": "user",
        "id": "8c4fdbe9-a093-423b-9b80-211cd139586b"
      },
      "last_edited_by": {
        "object": "user",
        "id": "8c4fdbe9-a093-423b-9b80-211cd139586b"
      },
      "has_children": false,
      "in_trash": false,
      "type": "paragraph",
      "paragraph": {
        "rich_text": [
          {
            "type": "text",
            "text": {
              "content": "Yannick requested autonomous development of an AI Book Cover Creator as a hybrid Design App for the Weavy platform. Manus established comprehensive authentication systems, created detailed specifications for a 4-phase workflow (input collection, draft generation, human review, finalization), and delivered extensive documentation including build guides, JSON specifications, and reusable authentication infrastructure. Despite initial attempts at UI automation, the session focused on creating complete implementation documentation rather than the actual functional app.",
              "link": null
            },
            "annotations": {
              "bold": false,
              "italic": false,
              "strikethrough": false,
              "underline": false,
              "code": false,
              "color": "default"
            },
            "plain_text": "Yannick requested autonomous development of an AI Book Cover Creator as a hybrid Design App for the Weavy platform. Manus established comprehensive authentication systems, created detailed specifications for a 4-phase workflow (input collection, draft generation, human review, finalization), and delivered extensive documentation including build guides, JSON specifications, and reusable authentication infrastructure. Despite initial attempts at UI automation, the session focused on creating complete implementation documentation rather than the actual functional app.",
            "href": null
          }
        ],
        "icon": null,
        "color": "default"
      },
      "archived": false
    },
    {
      "object": "block",
      "id": "b7239141-013a-4c43-84c9-0ff000c70e36",
      "parent": {
        "type": "page_id",
        "page_id": "33d35e21-8cf8-8143-85bd-d525894a88d7"
      },
      "created_time": "2026-04-09T08:40:00.000Z",
      "last_edited_time": "2026-04-09T08:40:00.000Z",
      "created_by": {
        "object": "user",
        "id": "8c4fdbe9-a093-423b-9b80-211cd139586b"
      },
      "last_edited_by": {
        "object": "user",
        "id": "8c4fdbe9-a093-423b-9b80-211cd139586b"
      },
      "has_children": false,
      "in_trash": false,
      "type": "heading_2",
      "heading_2": {
        "rich_text": [
          {
            "type": "text",
            "text": {
              "content": "Context & Intent",
              "link": null
            },
            "annotations": {
              "bold": false,
              "italic": false,
              "strikethrough": false,
              "underline": false,
              "code": false,
              "color": "default"
            },
            "plain_text": "Context & Intent",
            "href": null
          }
        ],
        "is_toggleable": false,
        "color": "default"
      },
      "archived": false
    },
    {
      "object": "block",
      "id": "80bb57b1-a738-46ce-99fb-9ba05fc59bf0",
      "parent": {
        "type": "page_id",
        "page_id": "33d35e21-8cf8-8143-85bd-d525894a88d7"
      },
      "created_time": "2026-04-09T08:40:00.000Z",
      "last_edited_time": "2026-04-09T08:40:00.000Z",
      "created_by": {
        "object": "user",
        "id": "8c4fdbe9-a093-423b-9b80-211cd139586b"
      },
      "last_edited_by": {
        "object": "user",
        "id": "8c4fdbe9-a093-423b-9b80-211cd139586b"
      },
      "has_children": false,
      "in_trash": false,
      "type": "paragraph",
      "paragraph": {
        "rich_text": [
          {
            "type": "text",
            "text": {
              "content": "Yannick wanted Manus to autonomously build a complete AI Book Cover Creator Design App on Weavy platform with hybrid automation (AI generation + human review). The app should generate professional book covers with front/back/spine layouts, marketing assets, and print-ready PDFs.",
              "link": null
            },
            "annotations": {
              "bold": false,
              "italic": false,
              "strikethrough": false,
              "underline": false,
              "code": false,
              "color": "default"
            },
            "plain_text": "Yannick wanted Manus to autonomously build a complete AI Book Cover Creator Design App on Weavy platform with hybrid automation (AI generation + human review). The app should generate professional book covers with front/back/spine layouts, marketing assets, and print-ready PDFs.",
            "href": null
          }
        ],
        "icon": null,
        "color": "default"
      },
      "archived": false
    },
    {
      "object": "block",
      "id": "671e90be-5c75-441d-bb8c-4620122265c2",
      "parent": {
        "type": "page_id",
        "page_id": "33d35e21-8cf8-8143-85bd-d525894a88d7"
      },
      "created_time": "2026-04-09T08:40:00.000Z",
      "last_edited_time": "2026-04-09T08:40:00.000Z",
      "created_by": {
        "object": "user",
        "id": "8c4fdbe9-a093-423b-9b80-211cd139586b"
      },
      "last_edited_by": {
        "object": "user",
        "id": "8c4fdbe9-a093-423b-9b80-211cd139586b"
      },
      "has_children": false,
      "in_trash": false,
      "type": "heading_2",
      "heading_2": {
        "rich_text": [
          {
            "type": "text",
            "text": {
              "content": "What Was Done",
              "link": null
            },
            "annotations": {
              "bold": false,
              "italic": false,
              "strikethrough": false,
              "underline": false,
              "code": false,
              "color": "default"
            },
            "plain_text": "What Was Done",
            "href": null
          }
        ],
        "is_toggleable": false,
        "color": "default"
      },
      "archived": false
    },
    {
      "object": "block",
      "id": "926cf601-eee8-47d3-8fc6-193a16a86e85",
      "parent": {
        "type": "page_id",
        "page_id": "33d35e21-8cf8-8143-85bd-d525894a88d7"
      },
      "created_time": "2026-04-09T08:40:00.000Z",
      "last_edited_time": "2026-04-09T08:40:00.000Z",
      "created_by": {
        "object": "user",
        "id": "8c4fdbe9-a093-423b-9b80-211cd139586b"
      },
      "last_edited_by": {
        "object": "user",
        "id": "8c4fdbe9-a093-423b-9b80-211cd139586b"
      },
      "has_children": false,
      "in_trash": false,
      "type": "paragraph",
      "paragraph": {
        "rich_text": [
          {
            "type": "text",
            "text": {
              "content": "Created comprehensive authentication system with 30-day session persistence, developed complete 4-phase workflow specifications, established persistent credential management across chat sessions, created detailed build guides and JSON specifications, attempted UI automation via Playwright, and built extensive knowledge bases for future sessions.",
              "link": null
            },
            "annotations": {
              "bold": false,
              "italic": false,
              "strikethrough": false,
              "underline": false,
              "code": false,
              "color": "default"
            },
            "plain_text": "Created comprehensive authentication system with 30-day session persistence, developed complete 4-phase workflow specifications, established persistent credential management across chat sessions, created detailed build guides and JSON specifications, attempted UI automation via Playwright, and built extensive knowledge bases for future sessions.",
            "href": null
          }
        ],
        "icon": null,
        "color": "default"
      },
      "archived": false
    },
    {
      "object": "block",
      "id": "f0bf82cf-7fad-4f19-809c-254d56bdb599",
      "parent": {
        "type": "page_id",
        "page_id": "33d35e21-8cf8-8143-85bd-d525894a88d7"
      },
      "created_time": "2026-04-09T08:40:00.000Z",
      "last_edited_time": "2026-04-09T08:40:00.000Z",
      "created_by": {
        "object": "user",
        "id": "8c4fdbe9-a093-423b-9b80-211cd139586b"
      },
      "last_edited_by": {
        "object": "user",
        "id": "8c4fdbe9-a093-423b-9b80-211cd139586b"
      },
      "has_children": false,
      "in_trash": false,
      "type": "heading_2",
      "heading_2": {
        "rich_text": [
          {
            "type": "text",
            "text": {
              "content": "Outputs Produced",
              "link": null
            },
            "annotations": {
              "bold": false,
              "italic": false,
              "strikethrough": false,
              "underline": false,
              "code": false,
              "color": "default"
            },
            "plain_text": "Outputs Produced",
            "href": null
          }
        ],
        "is_toggleable": false,
        "color": "default"
      },
      "archived": false
    },
    {
      "object": "block",
      "id": "26888a52-d914-4d02-8652-091a742f3f2d",
      "parent": {
        "type": "page_id",
        "page_id": "33d35e21-8cf8-8143-85bd-d525894a88d7"
      },
      "created_time": "2026-04-09T08:40:00.000Z",
      "last_edited_time": "2026-04-09T08:40:00.000Z",
      "created_by": {
        "object": "user",
        "id": "8c4fdbe9-a093-423b-9b80-211cd139586b"
      },
      "last_edited_by": {
        "object": "user",
        "id": "8c4fdbe9-a093-423b-9b80-211cd139586b"
      },
      "has_children": false,
      "in_trash": false,
      "type": "bulleted_list_item",
      "bulleted_list_item": {
        "rich_text": [
          {
            "type": "text",
            "text": {
              "content": "[documentation]",
              "link": null
            },
            "annotations": {
              "bold": true,
              "italic": false,
              "strikethrough": false,
              "underline": false,
              "code": false,
              "color": "default"
            },
            "plain_text": "[documentation]",
            "href": null
          },
          {
            "type": "text",
            "text": {
              "content": " WEAVY_ULTIMATE_BUILD_",
              "link": null
            },
            "annotations": {
              "bold": false,
              "italic": false,
              "strikethrough": false,
              "underline": false,
              "code": false,
              "color": "default"
            },
            "plain_text": " WEAVY_ULTIMATE_BUILD_",
            "href": null
          },
          {
            "type": "text",
            "text": {
              "content": "GUIDE.md",
              "link": {
                "url": "http://guide.md/"
              }
            },
            "annotations": {
              "bold": false,
              "italic": false,
              "strikethrough": false,
              "underline": false,
              "code": false,
              "color": "default"
            },
            "plain_text": "GUIDE.md",
            "href": "http://guide.md/"
          },
          {
            "type": "text",
            "text": {
              "content": " — Complete step-by-step manual build guide for the Design App",
              "link": null
            },
            "annotations": {
              "bold": false,
              "italic": false,
              "strikethrough": false,
              "underline": false,
              "code": false,
              "color": "default"
            },
            "plain_text": " — Complete step-by-step manual build guide for the Design App",
            "href": null
          }
        ],
        "color": "default"
      },
      "archived": false
    },
    {
      "object": "block",
      "id": "3f7bcd4f-0805-4c25-94df-783e0237fcf1",
      "parent": {
        "type": "page_id",
        "page_id": "33d35e21-8cf8-8143-85bd-d525894a88d7"
      },
      "created_time": "2026-04-09T08:40:00.000Z",
      "last_edited_time": "2026-04-09T08:40:00.000Z",
      "created_by": {
        "object": "user",
        "id": "8c4fdbe9-a093-423b-9b80-211cd139586b"
      },
      "last_edited_by": {
        "object": "user",
        "id": "8c4fdbe9-a093-423b-9b80-211cd139586b"
      },
      "has_children": false,
      "in_trash": false,
      "type": "bulleted_list_item",
      "bulleted_list_item": {
        "rich_text": [
          {
            "type": "text",
            "text": {
              "content": "[specification]",
              "link": null
            },
            "annotations": {
              "bold": true,
              "italic": false,
              "strikethrough": false,
              "underline": false,
              "code": false,
              "color": "default"
            },
            "plain_text": "[specification]",
            "href": null
          },
          {
            "type": "text",
            "text": {
              "content": " WEAVY_DESIGN_APP_COMPLETE.json — Technical JSON specification of the 4-phase workflow",
              "link": null
            },
            "annotations": {
              "bold": false,
              "italic": false,
              "strikethrough": false,
              "underline": false,
              "code": false,
              "color": "default"
            },
            "plain_text": " WEAVY_DESIGN_APP_COMPLETE.json — Technical JSON specification of the 4-phase workflow",
            "href": null
          }
        ],
        "color": "default"
      },
      "archived": false
    },
    {
      "object": "block",
      "id": "45f0c581-ad56-49b1-94a3-4c00a55d08ea",
      "parent": {
        "type": "page_id",
        "page_id": "33d35e21-8cf8-8143-85bd-d525894a88d7"
      },
      "created_time": "2026-04-09T08:40:00.000Z",
      "last_edited_time": "2026-04-09T08:40:00.000Z",
      "created_by": {
        "object": "user",
        "id": "8c4fdbe9-a093-423b-9b80-211cd139586b"
      },
      "last_edited_by": {
        "object": "user",
        "id": "8c4fdbe9-a093-423b-9b80-211cd139586b"
      },
      "has_children": false,
      "in_trash": false,
      "type": "bulleted_list_item",
      "bulleted_list_item": {
        "rich_text": [
          {
            "type": "text",
            "text": {
              "content": "[system]",
              "link": null
            },
            "annotations": {
              "bold": true,
              "italic": false,
              "strikethrough": false,
              "underline": false,
              "code": false,
              "color": "default"
            },
            "plain_text": "[system]",
            "href": null
          },
          {
            "type": "text",
            "text": {
              "content": " Authentication Agent — Reusable authentication system with 1Password integration and credential storage",
              "link": null
            },
            "annotations": {
              "bold": false,
              "italic": false,
              "strikethrough": false,
              "underline": false,
              "code": false,
              "color": "default"
            },
            "plain_text": " Authentication Agent — Reusable authentication system with 1Password integration and credential storage",
            "href": null
          }
        ],
        "color": "default"
      },
      "archived": false
    },
    {
      "object": "block",
      "id": "4387a7de-4365-463f-9f13-edb166f79fae",
      "parent": {
        "type": "page_id",
        "page_id": "33d35e21-8cf8-8143-85bd-d525894a88d7"
      },
      "created_time": "2026-04-09T08:40:00.000Z",
      "last_edited_time": "2026-04-09T08:40:00.000Z",
      "created_by": {
        "object": "user",
        "id": "8c4fdbe9-a093-423b-9b80-211cd139586b"
      },
      "last_edited_by": {
        "object": "user",
        "id": "8c4fdbe9-a093-423b-9b80-211cd139586b"
      },
      "has_children": false,
      "in_trash": false,
      "type": "bulleted_list_item",
      "bulleted_list_item": {
        "rich_text": [
          {
            "type": "text",
            "text": {
              "content": "[documentation]",
              "link": null
            },
            "annotations": {
              "bold": true,
              "italic": false,
              "strikethrough": false,
              "underline": false,
              "code": false,
              "color": "default"
            },
            "plain_text": "[documentation]",
            "href": null
          },
          {
            "type": "text",
            "text": {
              "content": " Multiple implementation guides — Comprehensive documentation package for project continuation",
              "link": null
            },
            "annotations": {
              "bold": false,
              "italic": false,
              "strikethrough": false,
              "underline": false,
              "code": false,
              "color": "default"
            },
            "plain_text": " Multiple implementation guides — Comprehensive documentation package for project continuation",
            "href": null
          }
        ],
        "color": "default"
      },
      "archived": false
    },
    {
      "object": "block",
      "id": "0d527949-72ae-4a4a-8d6f-f4aaacfa36e8",
      "parent": {
        "type": "page_id",
        "page_id": "33d35e21-8cf8-8143-85bd-d525894a88d7"
      },
      "created_time": "2026-04-09T08:40:00.000Z",
      "last_edited_time": "2026-04-09T08:40:00.000Z",
      "created_by": {
        "object": "user",
        "id": "8c4fdbe9-a093-423b-9b80-211cd139586b"
      },
      "last_edited_by": {
        "object": "user",
        "id": "8c4fdbe9-a093-423b-9b80-211cd139586b"
      },
      "has_children": false,
      "in_trash": false,
      "type": "bulleted_list_item",
      "bulleted_list_item": {
        "rich_text": [
          {
            "type": "text",
            "text": {
              "content": "[infrastructure]",
              "link": null
            },
            "annotations": {
              "bold": true,
              "italic": false,
              "strikethrough": false,
              "underline": false,
              "code": false,
              "color": "default"
            },
            "plain_text": "[infrastructure]",
            "href": null
          },
          {
            "type": "text",
            "text": {
              "content": " Knowledge base system — Persistent storage system for project specifications across sessions",
              "link": null
            },
            "annotations": {
              "bold": false,
              "italic": false,
              "strikethrough": false,
              "underline": false,
              "code": false,
              "color": "default"
            },
            "plain_text": " Knowledge base system — Persistent storage system for project specifications across sessions",
            "href": null
          }
        ],
        "color": "default"
      },
      "archived": false
    },
    {
      "object": "block",
      "id": "4912e372-6f10-4ab5-9354-c0832c914a15",
      "parent": {
        "type": "page_id",
        "page_id": "33d35e21-8cf8-8143-85bd-d525894a88d7"
      },
      "created_time": "2026-04-09T08:40:00.000Z",
      "last_edited_time": "2026-04-09T08:40:00.000Z",
      "created_by": {
        "object": "user",
        "id": "8c4fdbe9-a093-423b-9b80-211cd139586b"
      },
      "last_edited_by": {
        "object": "user",
        "id": "8c4fdbe9-a093-423b-9b80-211cd139586b"
      },
      "has_children": false,
      "in_trash": false,
      "type": "heading_2",
      "heading_2": {
        "rich_text": [
          {
            "type": "text",
            "text": {
              "content": "Key Decisions & Validations",
              "link": null
            },
            "annotations": {
              "bold": false,
              "italic": false,
              "strikethrough": false,
              "underline": false,
              "code": false,
              "color": "default"
            },
            "plain_text": "Key Decisions & Validations",
            "href": null
          }
        ],
        "is_toggleable": false,
        "color": "default"
      },
      "archived": false
    },
    {
      "object": "block",
      "id": "0b32ca28-def7-4295-8c6d-e7ff54319b07",
      "parent": {
        "type": "page_id",
        "page_id": "33d35e21-8cf8-8143-85bd-d525894a88d7"
      },
      "created_time": "2026-04-09T08:40:00.000Z",
      "last_edited_time": "2026-04-09T08:40:00.000Z",
      "created_by": {
        "object": "user",
        "id": "8c4fdbe9-a093-423b-9b80-211cd139586b"
      },
      "last_edited_by": {
        "object": "user",
        "id": "8c4fdbe9-a093-423b-9b80-211cd139586b"
      },
      "has_children": false,
      "in_trash": false,
      "type": "bulleted_list_item",
      "bulleted_list_item": {
        "rich_text": [
          {
            "type": "text",
            "text": {
              "content": "Use hybrid automation pattern (automated generation + human review + automated finalization)",
              "link": null
            },
            "annotations": {
              "bold": false,
              "italic": false,
              "strikethrough": false,
              "underline": false,
              "code": false,
              "color": "default"
            },
            "plain_text": "Use hybrid automation pattern (automated generation + human review + automated finalization)",
            "href": null
          }
        ],
        "color": "default"
      },
      "archived": false
    },
    {
      "object": "block",
      "id": "ad7b61de-fba5-4e7f-9868-4fd9e652396c",
      "parent": {
        "type": "page_id",
        "page_id": "33d35e21-8cf8-8143-85bd-d525894a88d7"
      },
      "created_time": "2026-04-09T08:40:00.000Z",
      "last_edited_time": "2026-04-09T08:40:00.000Z",
      "created_by": {
        "object": "user",
        "id": "8c4fdbe9-a093-423b-9b80-211cd139586b"
      },
      "last_edited_by": {
        "object": "user",
        "id": "8c4fdbe9-a093-423b-9b80-211cd139586b"
      },
      "has_children": false,
      "in_trash": false,
      "type": "bulleted_list_item",
      "bulleted_list_item": {
        "rich_text": [
          {
            "type": "text",
            "text": {
              "content": "Implement 30-day browser session persistence to reduce authentication friction",
              "link": null
            },
            "annotations": {
              "bold": false,
              "italic": false,
              "strikethrough": false,
              "underline": false,
              "code": false,
              "color": "default"
            },
            "plain_text": "Implement 30-day browser session persistence to reduce authentication friction",
            "href": null
          }
        ],
        "color": "default"
      },
      "archived": false
    },
    {
      "object": "block",
      "id": "c500ba32-d0ad-4cfa-9928-264aed3b9819",
      "parent": {
        "type": "page_id",
        "page_id": "33d35e21-8cf8-8143-85bd-d525894a88d7"
      },
      "created_time": "2026-04-09T08:40:00.000Z",
      "last_edited_time": "2026-04-09T08:40:00.000Z",
      "created_by": {
        "object": "user",
        "id": "8c4fdbe9-a093-423b-9b80-211cd139586b"
      },
      "last_edited_by": {
        "object": "user",
        "id": "8c4fdbe9-a093-423b-9b80-211cd139586b"
      },
      "has_children": false,
      "in_trash": false,
      "type": "bulleted_list_item",
      "bulleted_list_item": {
        "rich_text": [
          {
            "type": "text",
            "text": {
              "content": "Create comprehensive documentation rather than continue struggling with UI automation",
              "link": null
            },
            "annotations": {
              "bold": false,
              "italic": false,
              "strikethrough": false,
              "underline": false,
              "code": false,
              "color": "default"
            },
            "plain_text": "Create comprehensive documentation rather than continue struggling with UI automation",
            "href": null
          }
        ],
        "color": "default"
      },
      "archived": false
    },
    {
      "object": "block",
      "id": "60fa3b8f-791a-420d-9267-5a96e318fa25",
      "parent": {
        "type": "page_id",
        "page_id": "33d35e21-8cf8-8143-85bd-d525894a88d7"
      },
      "created_time": "2026-04-09T08:40:00.000Z",
      "last_edited_time": "2026-04-09T08:40:00.000Z",
      "created_by": {
        "object": "user",
        "id": "8c4fdbe9-a093-423b-9b80-211cd139586b"
      },
      "last_edited_by": {
        "object": "user",
        "id": "8c4fdbe9-a093-423b-9b80-211cd139586b"
      },
      "has_children": false,
      "in_trash": false,
      "type": "bulleted_list_item",
      "bulleted_list_item": {
        "rich_text": [
          {
            "type": "text",
            "text": {
              "content": "Establish reusable authentication system for all future chat sessions",
              "link": null
            },
            "annotations": {
              "bold": false,
              "italic": false,
              "strikethrough": false,
              "underline": false,
              "code": false,
              "color": "default"
            },
            "plain_text": "Establish reusable authentication system for all future chat sessions",
            "href": null
          }
        ],
        "color": "default"
      },
      "archived": false
    },
    {
      "object": "block",
      "id": "cf7a7cab-af6e-4195-907e-4dc71146d498",
      "parent": {
        "type": "page_id",
        "page_id": "33d35e21-8cf8-8143-85bd-d525894a88d7"
      },
      "created_time": "2026-04-09T08:40:00.000Z",
      "last_edited_time": "2026-04-09T08:40:00.000Z",
      "created_by": {
        "object": "user",
        "id": "8c4fdbe9-a093-423b-9b80-211cd139586b"
      },
      "last_edited_by": {
        "object": "user",
        "id": "8c4fdbe9-a093-423b-9b80-211cd139586b"
      },
      "has_children": false,
      "in_trash": false,
      "type": "bulleted_list_item",
      "bulleted_list_item": {
        "rich_text": [
          {
            "type": "text",
            "text": {
              "content": "Store credentials in both Manus Secrets and local encrypted storage",
              "link": null
            },
            "annotations": {
              "bold": false,
              "italic": false,
              "strikethrough": false,
              "underline": false,
              "code": false,
              "color": "default"
            },
            "plain_text": "Store credentials in both Manus Secrets and local encrypted storage",
            "href": null
          }
        ],
        "color": "default"
      },
      "archived": false
    },
    {
      "object": "block",
      "id": "34036878-7c17-408a-85fe-eb321ba206e7",
      "parent": {
        "type": "page_id",
        "page_id": "33d35e21-8cf8-8143-85bd-d525894a88d7"
      },
      "created_time": "2026-04-09T08:40:00.000Z",
      "last_edited_time": "2026-04-09T08:40:00.000Z",
      "created_by": {
        "object": "user",
        "id": "8c4fdbe9-a093-423b-9b80-211cd139586b"
      },
      "last_edited_by": {
        "object": "user",
        "id": "8c4fdbe9-a093-423b-9b80-211cd139586b"
      },
      "has_children": false,
      "in_trash": false,
      "type": "heading_2",
      "heading_2": {
        "rich_text": [
          {
            "type": "text",
            "text": {
              "content": "Lessons Learned",
              "link": null
            },
            "annotations": {
              "bold": false,
              "italic": false,
              "strikethrough": false,
              "underline": false,
              "code": false,
              "color": "default"
            },
            "plain_text": "Lessons Learned",
            "href": null
          }
        ],
        "is_toggleable": false,
        "color": "default"
      },
      "archived": false
    },
    {
      "object": "block",
      "id": "e5341fda-e686-4a7e-981f-df3a7775a02e",
      "parent": {
        "type": "page_id",
        "page_id": "33d35e21-8cf8-8143-85bd-d525894a88d7"
      },
      "created_time": "2026-04-09T08:40:00.000Z",
      "last_edited_time": "2026-04-09T08:40:00.000Z",
      "created_by": {
        "object": "user",
        "id": "8c4fdbe9-a093-423b-9b80-211cd139586b"
      },
      "last_edited_by": {
        "object": "user",
        "id": "8c4fdbe9-a093-423b-9b80-211cd139586b"
      },
      "has_children": false,
      "in_trash": false,
      "type": "paragraph",
      "paragraph": {
        "rich_text": [
          {
            "type": "text",
            "text": {
              "content": "Worked well:",
              "link": null
            },
            "annotations": {
              "bold": true,
              "italic": false,
              "strikethrough": false,
              "underline": false,
              "code": false,
              "color": "default"
            },
            "plain_text": "Worked well:",
            "href": null
          }
        ],
        "icon": null,
        "color": "default"
      },
      "archived": false
    },
    {
      "object": "block",
      "id": "7451615c-4552-4d18-8667-99c67c28a3ef",
      "parent": {
        "type": "page_id",
        "page_id": "33d35e21-8cf8-8143-85bd-d525894a88d7"
      },
      "created_time": "2026-04-09T08:40:00.000Z",
      "last_edited_time": "2026-04-09T08:40:00.000Z",
      "created_by": {
        "object": "user",
        "id": "8c4fdbe9-a093-423b-9b80-211cd139586b"
      },
      "last_edited_by": {
        "object": "user",
        "id": "8c4fdbe9-a093-423b-9b80-211cd139586b"
      },
      "has_children": false,
      "in_trash": false,
      "type": "bulleted_list_item",
      "bulleted_list_item": {
        "rich_text": [
          {
            "type": "text",
            "text": {
              "content": "Comprehensive documentation and specification creation",
              "link": null
            },
            "annotations": {
              "bold": false,
              "italic": false,
              "strikethrough": false,
              "underline": false,
              "code": false,
              "color": "default"
            },
            "plain_text": "Comprehensive documentation and specification creation",
            "href": null
          }
        ],
        "color": "default"
      },
      "archived": false
    },
    {
      "object": "block",
      "id": "58de4918-8d99-4b1d-afcd-85e81638096c",
      "parent": {
        "type": "page_id",
        "page_id": "33d35e21-8cf8-8143-85bd-d525894a88d7"
      },
      "created_time": "2026-04-09T08:40:00.000Z",
      "last_edited_time": "2026-04-09T08:40:00.000Z",
      "created_by": {
        "object": "user",
        "id": "8c4fdbe9-a093-423b-9b80-211cd139586b"
      },
      "last_edited_by": {
        "object": "user",
        "id": "8c4fdbe9-a093-423b-9b80-211cd139586b"
      },
      "has_children": false,
      "in_trash": false,
      "type": "bulleted_list_item",
      "bulleted_list_item": {
        "rich_text": [
          {
            "type": "text",
            "text": {
              "content": "Persistent authentication system setup",
              "link": null
            },
            "annotations": {
              "bold": false,
              "italic": false,
              "strikethrough": false,
              "underline": false,
              "code": false,
              "color": "default"
            },
            "plain_text": "Persistent authentication system setup",
            "href": null
          }
        ],
        "color": "default"
      },
      "archived": false
    },
    {
      "object": "block",
      "id": "e7748608-d846-4800-82e8-a3f6b15c6ca2",
      "parent": {
        "type": "page_id",
        "page_id": "33d35e21-8cf8-8143-85bd-d525894a88d7"
      },
      "created_time": "2026-04-09T08:40:00.000Z",
      "last_edited_time": "2026-04-09T08:40:00.000Z",
      "created_by": {
        "object": "user",
        "id": "8c4fdbe9-a093-423b-9b80-211cd139586b"
      },
      "last_edited_by": {
        "object": "user",
        "id": "8c4fdbe9-a093-423b-9b80-211cd139586b"
      },
      "has_children": false,
      "in_trash": false,
      "type": "bulleted_list_item",
      "bulleted_list_item": {
        "rich_text": [
          {
            "type": "text",
            "text": {
              "content": "Knowledge base creation for session continuity",
              "link": null
            },
            "annotations": {
              "bold": false,
              "italic": false,
              "strikethrough": false,
              "underline": false,
              "code": false,
              "color": "default"
            },
            "plain_text": "Knowledge base creation for session continuity",
            "href": null
          }
        ],
        "color": "default"
      },
      "archived": false
    },
    {
      "object": "block",
      "id": "091bdfd4-884d-4302-a3bf-b36e2988acf9",
      "parent": {
        "type": "page_id",
        "page_id": "33d35e21-8cf8-8143-85bd-d525894a88d7"
      },
      "created_time": "2026-04-09T08:40:00.000Z",
      "last_edited_time": "2026-04-09T08:40:00.000Z",
      "created_by": {
        "object": "user",
        "id": "8c4fdbe9-a093-423b-9b80-211cd139586b"
      },
      "last_edited_by": {
        "object": "user",
        "id": "8c4fdbe9-a093-423b-9b80-211cd139586b"
      },
      "has_children": false,
      "in_trash": false,
      "type": "bulleted_list_item",
      "bulleted_list_item": {
        "rich_text": [
          {
            "type": "text",
            "text": {
              "content": "Status report template development",
              "link": null
            },
            "annotations": {
              "bold": false,
              "italic": false,
              "strikethrough": false,
              "underline": false,
              "code": false,
              "color": "default"
            },
            "plain_text": "Status report template development",
            "href": null
          }
        ],
        "color": "default"
      },
      "archived": false
    },
    {
      "object": "block",
      "id": "d66d932b-9b28-4708-a122-3a5e6dafd94d",
      "parent": {
        "type": "page_id",
        "page_id": "33d35e21-8cf8-8143-85bd-d525894a88d7"
      },
      "created_time": "2026-04-09T08:40:00.000Z",
      "last_edited_time": "2026-04-09T08:40:00.000Z",
      "created_by": {
        "object": "user",
        "id": "8c4fdbe9-a093-423b-9b80-211cd139586b"
      },
      "last_edited_by": {
        "object": "user",
        "id": "8c4fdbe9-a093-423b-9b80-211cd139586b"
      },
      "has_children": false,
      "in_trash": false,
      "type": "paragraph",
      "paragraph": {
        "rich_text": [
          {
            "type": "text",
            "text": {
              "content": "Failed / suboptimal:",
              "link": null
            },
            "annotations": {
              "bold": true,
              "italic": false,
              "strikethrough": false,
              "underline": false,
              "code": false,
              "color": "default"
            },
            "plain_text": "Failed / suboptimal:",
            "href": null
          }
        ],
        "icon": null,
        "color": "default"
      },
      "archived": false
    },
    {
      "object": "block",
      "id": "f499802d-15a7-4046-9ab2-8ed21d6cae9c",
      "parent": {
        "type": "page_id",
        "page_id": "33d35e21-8cf8-8143-85bd-d525894a88d7"
      },
      "created_time": "2026-04-09T08:40:00.000Z",
      "last_edited_time": "2026-04-09T08:40:00.000Z",
      "created_by": {
        "object": "user",
        "id": "8c4fdbe9-a093-423b-9b80-211cd139586b"
      },
      "last_edited_by": {
        "object": "user",
        "id": "8c4fdbe9-a093-423b-9b80-211cd139586b"
      },
      "has_children": false,
      "in_trash": false,
      "type": "bulleted_list_item",
      "bulleted_list_item": {
        "rich_text": [
          {
            "type": "text",
            "text": {
              "content": "UI automation via Playwright was unreliable for complex drag-and-drop interfaces",
              "link": null
            },
            "annotations": {
              "bold": false,
              "italic": false,
              "strikethrough": false,
              "underline": false,
              "code": false,
              "color": "default"
            },
            "plain_text": "UI automation via Playwright was unreliable for complex drag-and-drop interfaces",
            "href": null
          }
        ],
        "color": "default"
      },
      "archived": false
    },
    {
      "object": "block",
      "id": "3850a722-7f8a-4e28-8299-8b558f503fc4",
      "parent": {
        "type": "page_id",
        "page_id": "33d35e21-8cf8-8143-85bd-d525894a88d7"
      },
      "created_time": "2026-04-09T08:40:00.000Z",
      "last_edited_time": "2026-04-09T08:40:00.000Z",
      "created_by": {
        "object": "user",
        "id": "8c4fdbe9-a093-423b-9b80-211cd139586b"
      },
      "last_edited_by": {
        "object": "user",
        "id": "8c4fdbe9-a093-423b-9b80-211cd139586b"
      },
      "has_children": false,
      "in_trash": false,
      "type": "bulleted_list_item",
      "bulleted_list_item": {
        "rich_text": [
          {
            "type": "text",
            "text": {
              "content": "Spent too much time on automation instead of manual implementation",
              "link": null
            },
            "annotations": {
              "bold": false,
              "italic": false,
              "strikethrough": false,
              "underline": false,
              "code": false,
              "color": "default"
            },
            "plain_text": "Spent too much time on automation instead of manual implementation",
            "href": null
          }
        ],
        "color": "default"
      },
      "archived": false
    },
    {
      "object": "block",
      "id": "9aab5ccb-f92d-41c9-946a-601584bf8eea",
      "parent": {
        "type": "page_id",
        "page_id": "33d35e21-8cf8-8143-85bd-d525894a88d7"
      },
      "created_time": "2026-04-09T08:40:00.000Z",
      "last_edited_time": "2026-04-09T08:40:00.000Z",
      "created_by": {
        "object": "user",
        "id": "8c4fdbe9-a093-423b-9b80-211cd139586b"
      },
      "last_edited_by": {
        "object": "user",
        "id": "8c4fdbe9-a093-423b-9b80-211cd139586b"
      },
      "has_children": false,
      "in_trash": false,
      "type": "bulleted_list_item",
      "bulleted_list_item": {
        "rich_text": [
          {
            "type": "text",
            "text": {
              "content": "Over-documented instead of building the actual functional app",
              "link": null
            },
            "annotations": {
              "bold": false,
              "italic": false,
              "strikethrough": false,
              "underline": false,
              "code": false,
              "color": "default"
            },
            "plain_text": "Over-documented instead of building the actual functional app",
            "href": null
          }
        ],
        "color": "default"
      },
      "archived": false
    },
    {
      "object": "block",
      "id": "a695b347-d531-42a6-b289-3f0c9705102c",
      "parent": {
        "type": "page_id",
        "page_id": "33d35e21-8cf8-8143-85bd-d525894a88d7"
      },
      "created_time": "2026-04-09T08:40:00.000Z",
      "last_edited_time": "2026-04-09T08:40:00.000Z",
      "created_by": {
        "object": "user",
        "id": "8c4fdbe9-a093-423b-9b80-211cd139586b"
      },
      "last_edited_by": {
        "object": "user",
        "id": "8c4fdbe9-a093-423b-9b80-211cd139586b"
      },
      "has_children": false,
      "in_trash": false,
      "type": "paragraph",
      "paragraph": {
        "rich_text": [
          {
            "type": "text",
            "text": {
              "content": "Discoveries:",
              "link": null
            },
            "annotations": {
              "bold": true,
              "italic": false,
              "strikethrough": false,
              "underline": false,
              "code": false,
              "color": "default"
            },
            "plain_text": "Discoveries:",
            "href": null
          }
        ],
        "icon": null,
        "color": "default"
      },
      "archived": false
    },
    {
      "object": "block",
      "id": "d20f426f-0ccb-4f91-b945-b533c788c718",
      "parent": {
        "type": "page_id",
        "page_id": "33d35e21-8cf8-8143-85bd-d525894a88d7"
      },
      "created_time": "2026-04-09T08:40:00.000Z",
      "last_edited_time": "2026-04-09T08:40:00.000Z",
      "created_by": {
        "object": "user",
        "id": "8c4fdbe9-a093-423b-9b80-211cd139586b"
      },
      "last_edited_by": {
        "object": "user",
        "id": "8c4fdbe9-a093-423b-9b80-211cd139586b"
      },
      "has_children": false,
      "in_trash": false,
      "type": "bulleted_list_item",
      "bulleted_list_item": {
        "rich_text": [
          {
            "type": "text",
            "text": {
              "content": "Weavy's UI requires precise manual interaction that's difficult to automate",
              "link": null
            },
            "annotations": {
              "bold": false,
              "italic": false,
              "strikethrough": false,
              "underline": false,
              "code": false,
              "color": "default"
            },
            "plain_text": "Weavy's UI requires precise manual interaction that's difficult to automate",
            "href": null
          }
        ],
        "color": "default"
      },
      "archived": false
    },
    {
      "object": "block",
      "id": "de7c3c8e-522c-48ea-bec4-e7f727afce9b",
      "parent": {
        "type": "page_id",
        "page_id": "33d35e21-8cf8-8143-85bd-d525894a88d7"
      },
      "created_time": "2026-04-09T08:40:00.000Z",
      "last_edited_time": "2026-04-09T08:40:00.000Z",
      "created_by": {
        "object": "user",
        "id": "8c4fdbe9-a093-423b-9b80-211cd139586b"
      },
      "last_edited_by": {
        "object": "user",
        "id": "8c4fdbe9-a093-423b-9b80-211cd139586b"
      },
      "has_children": false,
      "in_trash": false,
      "type": "bulleted_list_item",
      "bulleted_list_item": {
        "rich_text": [
          {
            "type": "text",
            "text": {
              "content": "Hybrid automation workflows are powerful for creative tasks",
              "link": null
            },
            "annotations": {
              "bold": false,
              "italic": false,
              "strikethrough": false,
              "underline": false,
              "code": false,
              "color": "default"
            },
            "plain_text": "Hybrid automation workflows are powerful for creative tasks",
            "href": null
          }
        ],
        "color": "default"
      },
      "archived": false
    },
    {
      "object": "block",
      "id": "0b2f92ce-fe8a-4235-85ab-4df2dfee1544",
      "parent": {
        "type": "page_id",
        "page_id": "33d35e21-8cf8-8143-85bd-d525894a88d7"
      },
      "created_time": "2026-04-09T08:40:00.000Z",
      "last_edited_time": "2026-04-09T08:40:00.000Z",
      "created_by": {
        "object": "user",
        "id": "8c4fdbe9-a093-423b-9b80-211cd139586b"
      },
      "last_edited_by": {
        "object": "user",
        "id": "8c4fdbe9-a093-423b-9b80-211cd139586b"
      },
      "has_children": false,
      "in_trash": false,
      "type": "bulleted_list_item",
      "bulleted_list_item": {
        "rich_text": [
          {
            "type": "text",
            "text": {
              "content": "Session persistence and credential management are critical for autonomous operation",
              "link": null
            },
            "annotations": {
              "bold": false,
              "italic": false,
              "strikethrough": false,
              "underline": false,
              "code": false,
              "color": "default"
            },
            "plain_text": "Session persistence and credential management are critical for autonomous operation",
            "href": null
          }
        ],
        "color": "default"
      },
      "archived": false
    },
    {
      "object": "block",
      "id": "eaa82498-aab1-4334-b972-e7d4883bddf3",
      "parent": {
        "type": "page_id",
        "page_id": "33d35e21-8cf8-8143-85bd-d525894a88d7"
      },
      "created_time": "2026-04-09T08:40:00.000Z",
      "last_edited_time": "2026-04-09T08:40:00.000Z",
      "created_by": {
        "object": "user",
        "id": "8c4fdbe9-a093-423b-9b80-211cd139586b"
      },
      "last_edited_by": {
        "object": "user",
        "id": "8c4fdbe9-a093-423b-9b80-211cd139586b"
      },
      "has_children": false,
      "in_trash": false,
      "type": "heading_2",
      "heading_2": {
        "rich_text": [
          {
            "type": "text",
            "text": {
              "content": "Challenges & Blockers",
              "link": null
            },
            "annotations": {
              "bold": false,
              "italic": false,
              "strikethrough": false,
              "underline": false,
              "code": false,
              "color": "default"
            },
            "plain_text": "Challenges & Blockers",
            "href": null
          }
        ],
        "is_toggleable": false,
        "color": "default"
      },
      "archived": false
    },
    {
      "object": "block",
      "id": "5cb15d53-ae5a-4c2b-a480-6ed2818d2a29",
      "parent": {
        "type": "page_id",
        "page_id": "33d35e21-8cf8-8143-85bd-d525894a88d7"
      },
      "created_time": "2026-04-09T08:40:00.000Z",
      "last_edited_time": "2026-04-09T08:40:00.000Z",
      "created_by": {
        "object": "user",
        "id": "8c4fdbe9-a093-423b-9b80-211cd139586b"
      },
      "last_edited_by": {
        "object": "user",
        "id": "8c4fdbe9-a093-423b-9b80-211cd139586b"
      },
      "has_children": false,
      "in_trash": false,
      "type": "bulleted_list_item",
      "bulleted_list_item": {
        "rich_text": [
          {
            "type": "text",
            "text": {
              "content": "Weavy's complex drag-and-drop UI interface was resistant to automation",
              "link": null
            },
            "annotations": {
              "bold": false,
              "italic": false,
              "strikethrough": false,
              "underline": false,
              "code": false,
              "color": "default"
            },
            "plain_text": "Weavy's complex drag-and-drop UI interface was resistant to automation",
            "href": null
          }
        ],
        "color": "default"
      },
      "archived": false
    },
    {
      "object": "block",
      "id": "e3d2d91a-5675-41a2-aa0e-187b25179df7",
      "parent": {
        "type": "page_id",
        "page_id": "33d35e21-8cf8-8143-85bd-d525894a88d7"
      },
      "created_time": "2026-04-09T08:40:00.000Z",
      "last_edited_time": "2026-04-09T08:40:00.000Z",
      "created_by": {
        "object": "user",
        "id": "8c4fdbe9-a093-423b-9b80-211cd139586b"
      },
      "last_edited_by": {
        "object": "user",
        "id": "8c4fdbe9-a093-423b-9b80-211cd139586b"
      },
      "has_children": false,
      "in_trash": false,
      "type": "bulleted_list_item",
      "bulleted_list_item": {
        "rich_text": [
          {
            "type": "text",
            "text": {
              "content": "Authentication flow required manual 2FA completion",
              "link": null
            },
            "annotations": {
              "bold": false,
              "italic": false,
              "strikethrough": false,
              "underline": false,
              "code": false,
              "color": "default"
            },
            "plain_text": "Authentication flow required manual 2FA completion",
            "href": null
          }
        ],
        "color": "default"
      },
      "archived": false
    },
    {
      "object": "block",
      "id": "a48d1cd8-241b-4a6a-81d4-e0209844f48d",
      "parent": {
        "type": "page_id",
        "page_id": "33d35e21-8cf8-8143-85bd-d525894a88d7"
      },
      "created_time": "2026-04-09T08:40:00.000Z",
      "last_edited_time": "2026-04-09T08:40:00.000Z",
      "created_by": {
        "object": "user",
        "id": "8c4fdbe9-a093-423b-9b80-211cd139586b"
      },
      "last_edited_by": {
        "object": "user",
        "id": "8c4fdbe9-a093-423b-9b80-211cd139586b"
      },
      "has_children": false,
      "in_trash": false,
      "type": "bulleted_list_item",
      "bulleted_list_item": {
        "rich_text": [
          {
            "type": "text",
            "text": {
              "content": "Browser automation failed to reliably interact with dynamic UI elements",
              "link": null
            },
            "annotations": {
              "bold": false,
              "italic": false,
              "strikethrough": false,
              "underline": false,
              "code": false,
              "color": "default"
            },
            "plain_text": "Browser automation failed to reliably interact with dynamic UI elements",
            "href": null
          }
        ],
        "color": "default"
      },
      "archived": false
    },
    {
      "object": "block",
      "id": "0a741a3f-5929-4f36-831a-7daebf99de8f",
      "parent": {
        "type": "page_id",
        "page_id": "33d35e21-8cf8-8143-85bd-d525894a88d7"
      },
      "created_time": "2026-04-09T08:40:00.000Z",
      "last_edited_time": "2026-04-09T08:40:00.000Z",
      "created_by": {
        "object": "user",
        "id": "8c4fdbe9-a093-423b-9b80-211cd139586b"
      },
      "last_edited_by": {
        "object": "user",
        "id": "8c4fdbe9-a093-423b-9b80-211cd139586b"
      },
      "has_children": false,
      "in_trash": false,
      "type": "bulleted_list_item",
      "bulleted_list_item": {
        "rich_text": [
          {
            "type": "text",
            "text": {
              "content": "User expected actual functional app but received documentation instead",
              "link": null
            },
            "annotations": {
              "bold": false,
              "italic": false,
              "strikethrough": false,
              "underline": false,
              "code": false,
              "color": "default"
            },
            "plain_text": "User expected actual functional app but received documentation instead",
            "href": null
          }
        ],
        "color": "default"
      },
      "archived": false
    },
    {
      "object": "block",
      "id": "7e3a39b5-7282-4f3a-841f-585e84c80b34",
      "parent": {
        "type": "page_id",
        "page_id": "33d35e21-8cf8-8143-85bd-d525894a88d7"
      },
      "created_time": "2026-04-09T08:40:00.000Z",
      "last_edited_time": "2026-04-09T08:40:00.000Z",
      "created_by": {
        "object": "user",
        "id": "8c4fdbe9-a093-423b-9b80-211cd139586b"
      },
      "last_edited_by": {
        "object": "user",
        "id": "8c4fdbe9-a093-423b-9b80-211cd139586b"
      },
      "has_children": false,
      "in_trash": false,
      "type": "heading_2",
      "heading_2": {
        "rich_text": [
          {
            "type": "text",
            "text": {
              "content": "Open Questions",
              "link": null
            },
            "annotations": {
              "bold": false,
              "italic": false,
              "strikethrough": false,
              "underline": false,
              "code": false,
              "color": "default"
            },
            "plain_text": "Open Questions",
            "href": null
          }
        ],
        "is_toggleable": false,
        "color": "default"
      },
      "archived": false
    },
    {
      "object": "block",
      "id": "ef9890ed-3dca-4294-9a5c-99054ee989a0",
      "parent": {
        "type": "page_id",
        "page_id": "33d35e21-8cf8-8143-85bd-d525894a88d7"
      },
      "created_time": "2026-04-09T08:40:00.000Z",
      "last_edited_time": "2026-04-09T08:40:00.000Z",
      "created_by": {
        "object": "user",
        "id": "8c4fdbe9-a093-423b-9b80-211cd139586b"
      },
      "last_edited_by": {
        "object": "user",
        "id": "8c4fdbe9-a093-423b-9b80-211cd139586b"
      },
      "has_children": false,
      "in_trash": false,
      "type": "bulleted_list_item",
      "bulleted_list_item": {
        "rich_text": [
          {
            "type": "text",
            "text": {
              "content": "How to effectively automate complex creative platform UIs like Weavy?",
              "link": null
            },
            "annotations": {
              "bold": false,
              "italic": false,
              "strikethrough": false,
              "underline": false,
              "code": false,
              "color": "default"
            },
            "plain_text": "How to effectively automate complex creative platform UIs like Weavy?",
            "href": null
          }
        ],
        "color": "default"
      },
      "archived": false
    },
    {
      "object": "block",
      "id": "07ed1467-e077-4ba3-aa80-858607d1f0ee",
      "parent": {
        "type": "page_id",
        "page_id": "33d35e21-8cf8-8143-85bd-d525894a88d7"
      },
      "created_time": "2026-04-09T08:40:00.000Z",
      "last_edited_time": "2026-04-09T08:40:00.000Z",
      "created_by": {
        "object": "user",
        "id": "8c4fdbe9-a093-423b-9b80-211cd139586b"
      },
      "last_edited_by": {
        "object": "user",
        "id": "8c4fdbe9-a093-423b-9b80-211cd139586b"
      },
      "has_children": false,
      "in_trash": false,
      "type": "bulleted_list_item",
      "bulleted_list_item": {
        "rich_text": [
          {
            "type": "text",
            "text": {
              "content": "Should future sessions prioritize manual implementation over automation attempts?",
              "link": null
            },
            "annotations": {
              "bold": false,
              "italic": false,
              "strikethrough": false,
              "underline": false,
              "code": false,
              "color": "default"
            },
            "plain_text": "Should future sessions prioritize manual implementation over automation attempts?",
            "href": null
          }
        ],
        "color": "default"
      },
      "archived": false
    },
    {
      "object": "block",
      "id": "1f03b784-a597-4bd4-83ad-53f077dddaf9",
      "parent": {
        "type": "page_id",
        "page_id": "33d35e21-8cf8-8143-85bd-d525894a88d7"
      },
      "created_time": "2026-04-09T08:40:00.000Z",
      "last_edited_time": "2026-04-09T08:40:00.000Z",
      "created_by": {
        "object": "user",
        "id": "8c4fdbe9-a093-423b-9b80-211cd139586b"
      },
      "last_edited_by": {
        "object": "user",
        "id": "8c4fdbe9-a093-423b-9b80-211cd139586b"
      },
      "has_children": false,
      "in_trash": false,
      "type": "bulleted_list_item",
      "bulleted_list_item": {
        "rich_text": [
          {
            "type": "text",
            "text": {
              "content": "What's the optimal balance between documentation and actual implementation?",
              "link": null
            },
            "annotations": {
              "bold": false,
              "italic": false,
              "strikethrough": false,
              "underline": false,
              "code": false,
              "color": "default"
            },
            "plain_text": "What's the optimal balance between documentation and actual implementation?",
            "href": null
          }
        ],
        "color": "default"
      },
      "archived": false
    },
    {
      "object": "block",
      "id": "6ef3d0d9-6765-4bc2-939f-46de6a1b6d74",
      "parent": {
        "type": "page_id",
        "page_id": "33d35e21-8cf8-8143-85bd-d525894a88d7"
      },
      "created_time": "2026-04-09T08:40:00.000Z",
      "last_edited_time": "2026-04-09T08:40:00.000Z",
      "created_by": {
        "object": "user",
        "id": "8c4fdbe9-a093-423b-9b80-211cd139586b"
      },
      "last_edited_by": {
        "object": "user",
        "id": "8c4fdbe9-a093-423b-9b80-211cd139586b"
      },
      "has_children": false,
      "in_trash": false,
      "type": "bulleted_list_item",
      "bulleted_list_item": {
        "rich_text": [
          {
            "type": "text",
            "text": {
              "content": "How to make hybrid automation workflows more seamless for users?",
              "link": null
            },
            "annotations": {
              "bold": false,
              "italic": false,
              "strikethrough": false,
              "underline": false,
              "code": false,
              "color": "default"
            },
            "plain_text": "How to make hybrid automation workflows more seamless for users?",
            "href": null
          }
        ],
        "color": "default"
      },
      "archived": false
    },
    {
      "object": "block",
      "id": "e9c138c9-852f-48e8-bbdc-188b65cd820f",
      "parent": {
        "type": "page_id",
        "page_id": "33d35e21-8cf8-8143-85bd-d525894a88d7"
      },
      "created_time": "2026-04-09T08:40:00.000Z",
      "last_edited_time": "2026-04-09T08:40:00.000Z",
      "created_by": {
        "object": "user",
        "id": "8c4fdbe9-a093-423b-9b80-211cd139586b"
      },
      "last_edited_by": {
        "object": "user",
        "id": "8c4fdbe9-a093-423b-9b80-211cd139586b"
      },
      "has_children": false,
      "in_trash": false,
      "type": "heading_2",
      "heading_2": {
        "rich_text": [
          {
            "type": "text",
            "text": {
              "content": "Next Steps",
              "link": null
            },
            "annotations": {
              "bold": false,
              "italic": false,
              "strikethrough": false,
              "underline": false,
              "code": false,
              "color": "default"
            },
            "plain_text": "Next Steps",
            "href": null
          }
        ],
        "is_toggleable": false,
        "color": "default"
      },
      "archived": false
    },
    {
      "object": "block",
      "id": "e2a6e190-25d5-4c41-aabc-78c03311a2bd",
      "parent": {
        "type": "page_id",
        "page_id": "33d35e21-8cf8-8143-85bd-d525894a88d7"
      },
      "created_time": "2026-04-09T08:40:00.000Z",
      "last_edited_time": "2026-04-09T08:40:00.000Z",
      "created_by": {
        "object": "user",
        "id": "8c4fdbe9-a093-423b-9b80-211cd139586b"
      },
      "last_edited_by": {
        "object": "user",
        "id": "8c4fdbe9-a093-423b-9b80-211cd139586b"
      },
      "has_children": false,
      "in_trash": false,
      "type": "bulleted_list_item",
      "bulleted_list_item": {
        "rich_text": [
          {
            "type": "text",
            "text": {
              "content": "Use the manual build guide to actually construct the Design App in Weavy",
              "link": null
            },
            "annotations": {
              "bold": false,
              "italic": false,
              "strikethrough": false,
              "underline": false,
              "code": false,
              "color": "default"
            },
            "plain_text": "Use the manual build guide to actually construct the Design App in Weavy",
            "href": null
          }
        ],
        "color": "default"
      },
      "archived": false
    },
    {
      "object": "block",
      "id": "9069802e-08e5-4fca-9c9c-2d19e2369590",
      "parent": {
        "type": "page_id",
        "page_id": "33d35e21-8cf8-8143-85bd-d525894a88d7"
      },
      "created_time": "2026-04-09T08:40:00.000Z",
      "last_edited_time": "2026-04-09T08:40:00.000Z",
      "created_by": {
        "object": "user",
        "id": "8c4fdbe9-a093-423b-9b80-211cd139586b"
      },
      "last_edited_by": {
        "object": "user",
        "id": "8c4fdbe9-a093-423b-9b80-211cd139586b"
      },
      "has_children": false,
      "in_trash": false,
      "type": "bulleted_list_item",
      "bulleted_list_item": {
        "rich_text": [
          {
            "type": "text",
            "text": {
              "content": "Test the 4-phase workflow with the provided sample book",
              "link": null
            },
            "annotations": {
              "bold": false,
              "italic": false,
              "strikethrough": false,
              "underline": false,
              "code": false,
              "color": "default"
            },
            "plain_text": "Test the 4-phase workflow with the provided sample book",
            "href": null
          }
        ],
        "color": "default"
      },
      "archived": false
    },
    {
      "object": "block",
      "id": "0da30808-7d54-4e87-b71b-bc70d78634fc",
      "parent": {
        "type": "page_id",
        "page_id": "33d35e21-8cf8-8143-85bd-d525894a88d7"
      },
      "created_time": "2026-04-09T08:40:00.000Z",
      "last_edited_time": "2026-04-09T08:40:00.000Z",
      "created_by": {
        "object": "user",
        "id": "8c4fdbe9-a093-423b-9b80-211cd139586b"
      },
      "last_edited_by": {
        "object": "user",
        "id": "8c4fdbe9-a093-423b-9b80-211cd139586b"
      },
      "has_children": false,
      "in_trash": false,
      "type": "bulleted_list_item",
      "bulleted_list_item": {
        "rich_text": [
          {
            "type": "text",
            "text": {
              "content": "Refine the authentication system for better automation",
              "link": null
            },
            "annotations": {
              "bold": false,
              "italic": false,
              "strikethrough": false,
              "underline": false,
              "code": false,
              "color": "default"
            },
            "plain_text": "Refine the authentication system for better automation",
            "href": null
          }
        ],
        "color": "default"
      },
      "archived": false
    },
    {
      "object": "block",
      "id": "3d4caa34-29a3-4af2-80fd-c151723d9c88",
      "parent": {
        "type": "page_id",
        "page_id": "33d35e21-8cf8-8143-85bd-d525894a88d7"
      },
      "created_time": "2026-04-09T08:40:00.000Z",
      "last_edited_time": "2026-04-09T08:40:00.000Z",
      "created_by": {
        "object": "user",
        "id": "8c4fdbe9-a093-423b-9b80-211cd139586b"
      },
      "last_edited_by": {
        "object": "user",
        "id": "8c4fdbe9-a093-423b-9b80-211cd139586b"
      },
      "has_children": false,
      "in_trash": false,
      "type": "bulleted_list_item",
      "bulleted_list_item": {
        "rich_text": [
          {
            "type": "text",
            "text": {
              "content": "Consider API-based approaches for platform integration instead of UI automation",
              "link": null
            },
            "annotations": {
              "bold": false,
              "italic": false,
              "strikethrough": false,
              "underline": false,
              "code": false,
              "color": "default"
            },
            "plain_text": "Consider API-based approaches for platform integration instead of UI automation",
            "href": null
          }
        ],
        "color": "default"
      },
      "archived": false
    },
    {
      "object": "block",
      "id": "01dc05bf-2169-48e4-8715-f062ac8820c9",
      "parent": {
        "type": "page_id",
        "page_id": "33d35e21-8cf8-8143-85bd-d525894a88d7"
      },
      "created_time": "2026-04-09T08:40:00.000Z",
      "last_edited_time": "2026-04-09T08:40:00.000Z",
      "created_by": {
        "object": "user",
        "id": "8c4fdbe9-a093-423b-9b80-211cd139586b"
      },
      "last_edited_by": {
        "object": "user",
        "id": "8c4fdbe9-a093-423b-9b80-211cd139586b"
      },
      "has_children": false,
      "in_trash": false,
      "type": "bulleted_list_item",
      "bulleted_list_item": {
        "rich_text": [
          {
            "type": "text",
            "text": {
              "content": "Implement the actual functional Design App following the comprehensive specifications",
              "link": null
            },
            "annotations": {
              "bold": false,
              "italic": false,
              "strikethrough": false,
              "underline": false,
              "code": false,
              "color": "default"
            },
            "plain_text": "Implement the actual functional Design App following the comprehensive specifications",
            "href": null
          }
        ],
        "color": "default"
      },
      "archived": false
    },
    {
      "object": "block",
      "id": "078f5bb5-81ab-42dc-b939-2e2c594ca867",
      "parent": {
        "type": "page_id",
        "page_id": "33d35e21-8cf8-8143-85bd-d525894a88d7"
      },
      "created_time": "2026-04-09T08:40:00.000Z",
      "last_edited_time": "2026-04-09T08:40:00.000Z",
      "created_by": {
        "object": "user",
        "id": "8c4fdbe9-a093-423b-9b80-211cd139586b"
      },
      "last_edited_by": {
        "object": "user",
        "id": "8c4fdbe9-a093-423b-9b80-211cd139586b"
      },
      "has_children": false,
      "in_trash": false,
      "type": "divider",
      "divider": {},
      "archived": false
    },
    {
      "object": "block",
      "id": "effa72ee-720a-4fdf-b2a6-87135a24ceb9",
      "parent": {
        "type": "page_id",
        "page_id": "33d35e21-8cf8-8143-85bd-d525894a88d7"
      },
      "created_time": "2026-04-09T08:40:00.000Z",
      "last_edited_time": "2026-04-09T08:40:00.000Z",
      "created_by": {
        "object": "user",
        "id": "8c4fdbe9-a093-423b-9b80-211cd139586b"
      },
      "last_edited_by": {
        "object": "user",
        "id": "8c4fdbe9-a093-423b-9b80-211cd139586b"
      },
      "has_children": false,
      "in_trash": false,
      "type": "paragraph",
      "paragraph": {
        "rich_text": [
          {
            "type": "text",
            "text": {
              "content": "UID: ",
              "link": null
            },
            "annotations": {
              "bold": false,
              "italic": true,
              "strikethrough": false,
              "underline": false,
              "code": false,
              "color": "default"
            },
            "plain_text": "UID: ",
            "href": null
          },
          {
            "type": "text",
            "text": {
              "content": "jrhRzGgvrCzLtezdHXURnC",
              "link": null
            },
            "annotations": {
              "bold": false,
              "italic": true,
              "strikethrough": false,
              "underline": false,
              "code": true,
              "color": "default"
            },
            "plain_text": "jrhRzGgvrCzLtezdHXURnC",
            "href": null
          },
          {
            "type": "text",
            "text": {
              "content": " | Model: claude-sonnet-4-20250514 | Cost: $0.0706",
              "link": null
            },
            "annotations": {
              "bold": false,
              "italic": true,
              "strikethrough": false,
              "underline": false,
              "code": false,
              "color": "default"
            },
            "plain_text": " | Model: claude-sonnet-4-20250514 | Cost: $0.0706",
            "href": null
          }
        ],
        "icon": null,
        "color": "default"
      },
      "archived": false
    }
  ],
  "markdown_content": "\n## Executive Summary\n\nYannick requested autonomous development of an AI Book Cover Creator as a hybrid Design App for the Weavy platform. Manus established comprehensive authentication systems, created detailed specifications for a 4-phase workflow (input collection, draft generation, human review, finalization), and delivered extensive documentation including build guides, JSON specifications, and reusable authentication infrastructure. Despite initial attempts at UI automation, the session focused on creating complete implementation documentation rather than the actual functional app.\n\n\n## Context & Intent\n\nYannick wanted Manus to autonomously build a complete AI Book Cover Creator Design App on Weavy platform with hybrid automation (AI generation + human review). The app should generate professional book covers with front/back/spine layouts, marketing assets, and print-ready PDFs.\n\n\n## What Was Done\n\nCreated comprehensive authentication system with 30-day session persistence, developed complete 4-phase workflow specifications, established persistent credential management across chat sessions, created detailed build guides and JSON specifications, attempted UI automation via Playwright, and built extensive knowledge bases for future sessions.\n\n\n## Outputs Produced\n\n- [documentation] WEAVY_ULTIMATE_BUILD_GUIDE.md — Complete step-by-step manual build guide for the Design App\n- [specification] WEAVY_DESIGN_APP_COMPLETE.json — Technical JSON specification of the 4-phase workflow\n- [system] Authentication Agent — Reusable authentication system with 1Password integration and credential storage\n- [documentation] Multiple implementation guides — Comprehensive documentation package for project continuation\n- [infrastructure] Knowledge base system — Persistent storage system for project specifications across sessions\n\n## Key Decisions & Validations\n\n- Use hybrid automation pattern (automated generation + human review + automated finalization)\n- Implement 30-day browser session persistence to reduce authentication friction\n- Create comprehensive documentation rather than continue struggling with UI automation\n- Establish reusable authentication system for all future chat sessions\n- Store credentials in both Manus Secrets and local encrypted storage\n\n## Lessons Learned\n\nWorked well:\n\n- Comprehensive documentation and specification creation\n- Persistent authentication system setup\n- Knowledge base creation for session continuity\n- Status report template development\nFailed / suboptimal:\n\n- UI automation via Playwright was unreliable for complex drag-and-drop interfaces\n- Spent too much time on automation instead of manual implementation\n- Over-documented instead of building the actual functional app\nDiscoveries:\n\n- Weavy's UI requires precise manual interaction that's difficult to automate\n- Hybrid automation workflows are powerful for creative tasks\n- Session persistence and credential management are critical for autonomous operation\n\n## Challenges & Blockers\n\n- Weavy's complex drag-and-drop UI interface was resistant to automation\n- Authentication flow required manual 2FA completion\n- Browser automation failed to reliably interact with dynamic UI elements\n- User expected actual functional app but received documentation instead\n\n## Open Questions\n\n- How to effectively automate complex creative platform UIs like Weavy?\n- Should future sessions prioritize manual implementation over automation attempts?\n- What's the optimal balance between documentation and actual implementation?\n- How to make hybrid automation workflows more seamless for users?\n\n## Next Steps\n\n- Use the manual build guide to actually construct the Design App in Weavy\n- Test the 4-phase workflow with the provided sample book\n- Refine the authentication system for better automation\n- Consider API-based approaches for platform integration instead of UI automation\n- Implement the actual functional Design App following the comprehensive specifications\n---\nUID: jrhRzGgvrCzLtezdHXURnC | Model: claude-sonnet-4-20250514 | Cost: $0.0706\n"
}